MANIFEST.in
README.rst
setup.py
collective/__init__.py
collective.dancingnotlikely.egg-info/PKG-INFO
collective.dancingnotlikely.egg-info/SOURCES.txt
collective.dancingnotlikely.egg-info/dependency_links.txt
collective.dancingnotlikely.egg-info/entry_points.txt
collective.dancingnotlikely.egg-info/namespace_packages.txt
collective.dancingnotlikely.egg-info/not-zip-safe
collective.dancingnotlikely.egg-info/requires.txt
collective.dancingnotlikely.egg-info/top_level.txt
collective/dancingnotlikely/__init__.py
collective/dancingnotlikely/configure.zcml
collective/dancingnotlikely/profiles/default/metadata.xml
docs/HISTORY.txt