Metadata-Version: 1.1
Name: collective.dancingnotlikely
Version: 1.0.1
Summary: A plugin for collective.dancing that add more elements to ignore-list in the composer
Home-page: http://svn.plone.org/svn/collective/
Author: RedTurtle Technology
Author-email: sviluppoplone@redturtle.it
License: GPL
Keywords: dancing newsletter composer filter
Platform: UNKNOWN
Classifier: Programming Language :: Python
